autodrp/__init__.py
autodrp/apps.py
autodrp/checks.py
autodrp/filters.py
autodrp/models.py
autodrp/utils.py
django_autodrp-1.0.0.dist-info/LICENSE
django_autodrp-1.0.0.dist-info/METADATA
django_autodrp-1.0.0.dist-info/WHEEL
django_autodrp-1.0.0.dist-info/top_level.txt
django_autodrp-1.0.0.dist-info/RECORD
