Metadata-Version: 2.1
Name: django-autodrp
Version: 1.0.0
Summary: Automatically set-up filters and permissions for Django's DRY Rest Permissions
Home-page: https://github.com/rcj0003/django-autodrp
Author: rcj0003
License: UNKNOWN
Platform: UNKNOWN
Classifier: Programming Language :: Python :: 3
Classifier: Framework :: Django :: 3.0
Classifier: Framework :: Django :: 3.2
Classifier: Framework :: Django :: 4.0
Classifier: Intended Audience :: Developers
Classifier: License :: OSI Approved :: BSD License
Requires-Python: >=3.5
License-File: LICENSE
Requires-Dist: django (>=3.0)
Requires-Dist: djangorestframework (>=3.12.4)
